README.rst
setup.py
sooty.py
sooty.egg-info/PKG-INFO
sooty.egg-info/SOURCES.txt
sooty.egg-info/dependency_links.txt
sooty.egg-info/entry_points.txt
sooty.egg-info/not-zip-safe
sooty.egg-info/requires.txt
sooty.egg-info/top_level.txt