Metadata-Version: 1.0
Name: sooty
Version: 0.0.1
Summary: Sooty: Simple database migrator.
Home-page: https://github.com/jzellman/sooty
Author: Jeff Zellman
Author-email: jzellman@gmail.com
License: Copyright (c) 2016, Jeff Zellman
